aiodagpi/__init__.py
aiodagpi/client.py
aiodagpi/enums.py
aiodagpi/exceptions.py
aiodagpi/http.py
aiodagpi/objects.py
aiodagpi-0.3.3.dist-info/LICENSE
aiodagpi-0.3.3.dist-info/METADATA
aiodagpi-0.3.3.dist-info/WHEEL
aiodagpi-0.3.3.dist-info/top_level.txt
aiodagpi-0.3.3.dist-info/RECORD
