Metadata-Version: 2.1
Name: aiodagpi
Version: 0.3.3
Summary: An asynchronous python API wrapper for Dagpi :                 https://dagpi.xyz
Home-page: https://github.com/DevilJamJar/aiodagpi
Author: Raj Sharma
Author-email: yrsharma@icloud.com
License: MIT
Keywords: dagpi,aiodagpi,async,aiohttp
Platform: UNKNOWN
Classifier: Development Status :: 4 - Beta
Classifier: License :: OSI Approved :: MIT License
Classifier: Programming Language :: Python
Classifier: Programming Language :: Python :: 3 :: Only
Classifier: Programming Language :: Python :: 3.6
Classifier: Programming Language :: Python :: 3.7
Classifier: Programming Language :: Python :: 3.8
Classifier: Programming Language :: Python :: 3.9
Classifier: Framework :: AsyncIO
Classifier: Intended Audience :: Developers
Classifier: Natural Language :: English
Classifier: Operating System :: OS Independent
Classifier: Topic :: Software Development :: Libraries :: Python Modules
Requires-Dist: aiohttp
